{"cameraMode":{"drawMode":2,"name":"Shaded Wireframe","section":"Shading Mode"},"sceneLighting":true,"audioPlay":false,"sceneViewState":{"m_AlwaysRefresh":false,"showFog":true,"showSkybox":true,"showFlares":true,"showImageEffects":true,"showParticleSystems":true,"showVisualEffectGraphs":true,"m_FxEnabled":true},"in2DMode":false,"pivot":{"x":74.59805297851563,"y":183.0727081298828,"z":118.76879119873047},"rotation":{"x":0.18005424737930299,"y":0.45725664496421816,"z":-0.09482970833778382,"w":0.8659189939498901},"size":683.6624145507813,"orthographic":false}